pyezvizapi/__init__.py
pyezvizapi/__main__.py
pyezvizapi/api_endpoints.py
pyezvizapi/camera.py
pyezvizapi/cas.py
pyezvizapi/client.py
pyezvizapi/constants.py
pyezvizapi/exceptions.py
pyezvizapi/feature.py
pyezvizapi/light_bulb.py
pyezvizapi/models.py
pyezvizapi/mqtt.py
pyezvizapi/smart_plug.py
pyezvizapi/test_cam_rtsp.py
pyezvizapi/test_mqtt.py
pyezvizapi/utils.py
pyezvizapi-1.0.4.4.dist-info/licenses/LICENSE
pyezvizapi-1.0.4.4.dist-info/licenses/LICENSE.md
pyezvizapi-1.0.4.4.dist-info/METADATA
pyezvizapi-1.0.4.4.dist-info/WHEEL
pyezvizapi-1.0.4.4.dist-info/top_level.txt
pyezvizapi-1.0.4.4.dist-info/RECORD
