Metadata-Version: 2.4
Name: pyezvizapi
Version: 1.0.4.4
Summary: EZVIZ API client for Home Assistant and CLI
Home-page: https://github.com/RenierM26/pyEzvizApi/
Author: Renier Moorcroft
Author-email: RenierM26@users.github.com
Requires-Python: >=3.11
License-File: LICENSE
License-File: LICENSE.md
Requires-Dist: requests
Requires-Dist: xmltodict
Requires-Dist: pycryptodome
Requires-Dist: paho-mqtt
Requires-Dist: pandas
Provides-Extra: dev
Requires-Dist: ruff; extra == "dev"
Requires-Dist: mypy; extra == "dev"
Requires-Dist: pytest; extra == "dev"
Requires-Dist: types-requests; extra == "dev"
Dynamic: author
Dynamic: author-email
Dynamic: home-page
Dynamic: license-file
Dynamic: requires-python
